{
  "collected_at": "2026-01-16T10:22:04.643551+00:00",
  "source": "amtraker.com",
  "total_trains": 7,
  "trains": [
    {
      "trainNum": "67",
      "routeName": "Northeast Regional",
      "lat": 39.70763815650396,
      "lon": -75.63445472485132,
      "heading": "W",
      "velocity": 118.16609954834,
      "lastUpdate": "2026-01-16T05:16:21-05:00",
      "nextStation": "Baltimore Penn",
      "status": "Active"
    },
    {
      "trainNum": "98",
      "routeName": "Silver Meteor",
      "lat": 38.676372632540044,
      "lon": -77.22922750022032,
      "heading": "N",
      "velocity": 24.2238235473633,
      "lastUpdate": "2026-01-16T05:18:19-05:00",
      "nextStation": "Alexandria",
      "status": "Active"
    },
    {
      "trainNum": "151",
      "routeName": "Northeast Regional",
      "lat": 39.73693885538488,
      "lon": -75.55071446521845,
      "heading": "NW",
      "velocity": 0.00894775986671448,
      "lastUpdate": "2026-01-16T05:18:21-05:00",
      "nextStation": "Wilmington",
      "status": "Active"
    },
    {
      "trainNum": "170",
      "routeName": "Northeast Regional",
      "lat": 39.03364963841181,
      "lon": -76.75235969748191,
      "heading": "NE",
      "velocity": 118.779273986816,
      "lastUpdate": "2026-01-16T05:18:19-05:00",
      "nextStation": "Baltimore Airport",
      "status": "Active"
    },
    {
      "trainNum": "601",
      "routeName": "Keystone",
      "lat": 39.96791883425787,
      "lon": -75.19290339217243,
      "heading": "W",
      "velocity": 27.96169090271,
      "lastUpdate": "2026-01-16T05:16:22-05:00",
      "nextStation": "Ardmore",
      "status": "Active"
    },
    {
      "trainNum": "640",
      "routeName": "Keystone",
      "lat": 40.146805229871106,
      "lon": -76.61300120279333,
      "heading": "SE",
      "velocity": 0.00223693996667862,
      "lastUpdate": "2026-01-16T05:18:21-05:00",
      "nextStation": "Elizabethtown",
      "status": "Active"
    },
    {
      "trainNum": "2150",
      "routeName": "Acela",
      "lat": 39.14218161427848,
      "lon": -76.69736701094305,
      "heading": "N",
      "velocity": 120.501724243164,
      "lastUpdate": "2026-01-16T05:18:21-05:00",
      "nextStation": "Baltimore Airport",
      "status": "Active"
    }
  ]
}