{
  "collected_at": "2026-01-16T03:20:15.573337+00:00",
  "source": "amtraker.com",
  "total_trains": 11,
  "trains": [
    {
      "trainNum": "55",
      "routeName": "Vermonter",
      "lat": 38.909031074025464,
      "lon": -77.00187148667061,
      "heading": "N",
      "velocity": 0,
      "lastUpdate": "2026-01-15T22:04:18-05:00",
      "nextStation": "Washington Union",
      "status": "Completed"
    },
    {
      "trainNum": "66",
      "routeName": "Northeast Regional",
      "lat": 38.898792423843666,
      "lon": -77.00501479702454,
      "heading": "N",
      "velocity": 0.0111846998333931,
      "lastUpdate": "2026-01-15T22:18:20-05:00",
      "nextStation": "Washington Union",
      "status": "Active"
    },
    {
      "trainNum": "175",
      "routeName": "Northeast Regional",
      "lat": 39.37765149213858,
      "lon": -76.35604306655924,
      "heading": "SW",
      "velocity": 117.569091796875,
      "lastUpdate": "2026-01-15T22:18:23-05:00",
      "nextStation": "Baltimore Penn",
      "status": "Active"
    },
    {
      "trainNum": "186",
      "routeName": "Northeast Regional",
      "lat": 39.86462825059702,
      "lon": -75.33538237396984,
      "heading": "NE",
      "velocity": 5.37536668777466,
      "lastUpdate": "2026-01-15T22:18:23-05:00",
      "nextStation": "Philadelphia 30th Street",
      "status": "Active"
    },
    {
      "trainNum": "198",
      "routeName": "Northeast Regional",
      "lat": 39.45409041673131,
      "lon": -76.21237389718073,
      "heading": "NE",
      "velocity": 122.830375671387,
      "lastUpdate": "2026-01-15T22:18:23-05:00",
      "nextStation": "Wilmington",
      "status": "Active"
    },
    {
      "trainNum": "622",
      "routeName": "Keystone",
      "lat": 40.00225872625164,
      "lon": -75.7095432676937,
      "heading": "E",
      "velocity": 0,
      "lastUpdate": "2026-01-15T22:18:22-05:00",
      "nextStation": "Downingtown",
      "status": "Active"
    },
    {
      "trainNum": "626",
      "routeName": "Keystone",
      "lat": 40.005070179998235,
      "lon": -75.1271303636005,
      "heading": "E",
      "velocity": 63.0928916931152,
      "lastUpdate": "2026-01-15T22:18:13-05:00",
      "nextStation": "Newark Penn",
      "status": "Active"
    },
    {
      "trainNum": "639",
      "routeName": "Keystone",
      "lat": 39.98714109763462,
      "lon": -75.17730127740192,
      "heading": "SW",
      "velocity": 67.9828414916992,
      "lastUpdate": "2026-01-15T22:18:23-05:00",
      "nextStation": "Philadelphia 30th Street",
      "status": "Active"
    },
    {
      "trainNum": "655",
      "routeName": "Keystone",
      "lat": 40.25884671571192,
      "lon": -76.87565845877138,
      "heading": "N",
      "velocity": 0,
      "lastUpdate": "2026-01-15T22:04:18-05:00",
      "nextStation": "Harrisburg",
      "status": "Completed"
    },
    {
      "trainNum": "657",
      "routeName": "Keystone",
      "lat": 40.00492903119742,
      "lon": -75.25942410649381,
      "heading": "W",
      "velocity": 57.9099044799805,
      "lastUpdate": "2026-01-15T22:18:17-05:00",
      "nextStation": "Ardmore",
      "status": "Active"
    },
    {
      "trainNum": "2171",
      "routeName": "Acela",
      "lat": 38.90489212612861,
      "lon": -77.00354232393829,
      "heading": "N",
      "velocity": 0,
      "lastUpdate": "2026-01-15T22:13:18-05:00",
      "nextStation": "Washington Union",
      "status": "Completed"
    }
  ]
}