{
  "collected_at": "2026-01-17T14:17:24.870311+00:00",
  "source": "amtraker.com",
  "total_trains": 16,
  "trains": [
    {
      "trainNum": "54",
      "routeName": "Vermonter",
      "lat": 39.94126553842712,
      "lon": -75.20786463828753,
      "heading": "NE",
      "velocity": 47.228515625,
      "lastUpdate": "2026-01-17T09:15:32-05:00",
      "nextStation": "Philadelphia 30th Street",
      "status": "Active"
    },
    {
      "trainNum": "79",
      "routeName": "Carolinian",
      "lat": 39.74172248796517,
      "lon": -75.53342625205359,
      "heading": "SW",
      "velocity": 48.9710922241211,
      "lastUpdate": "2026-01-17T09:15:29-05:00",
      "nextStation": "Wilmington",
      "status": "Active"
    },
    {
      "trainNum": "89",
      "routeName": "Palmetto",
      "lat": 38.98988742040064,
      "lon": -76.81157907329155,
      "heading": "SW",
      "velocity": 111.023803710938,
      "lastUpdate": "2026-01-17T09:15:31-05:00",
      "nextStation": "Washington Union",
      "status": "Active"
    },
    {
      "trainNum": "101",
      "routeName": "Northeast Regional",
      "lat": 39.95560880423632,
      "lon": -75.18118463771279,
      "heading": "S",
      "velocity": 0,
      "lastUpdate": "2026-01-17T09:15:26-05:00",
      "nextStation": "Philadelphia 30th Street",
      "status": "Active"
    },
    {
      "trainNum": "151",
      "routeName": "Northeast Regional",
      "lat": 38.285129539783014,
      "lon": -78.09086104306378,
      "heading": "SW",
      "velocity": 59.3370704650879,
      "lastUpdate": "2026-01-17T09:15:35-05:00",
      "nextStation": "Charlottesville",
      "status": "Active"
    },
    {
      "trainNum": "152",
      "routeName": "Northeast Regional",
      "lat": 39.3286135453494,
      "lon": -76.46338104818331,
      "heading": "E",
      "velocity": 99.3022384643555,
      "lastUpdate": "2026-01-17T09:15:36-05:00",
      "nextStation": "Newark",
      "status": "Active"
    },
    {
      "trainNum": "164",
      "routeName": "Northeast Regional",
      "lat": 38.91257111398097,
      "lon": -76.99538649886695,
      "heading": "NE",
      "velocity": 42.799373626709,
      "lastUpdate": "2026-01-17T09:15:35-05:00",
      "nextStation": "New Carrollton",
      "status": "Active"
    },
    {
      "trainNum": "611",
      "routeName": "Keystone",
      "lat": 40.19638485571812,
      "lon": -76.74016799404347,
      "heading": "W",
      "velocity": 16.35426902771,
      "lastUpdate": "2026-01-17T09:15:34-05:00",
      "nextStation": "Harrisburg",
      "status": "Active"
    },
    {
      "trainNum": "660",
      "routeName": "Keystone",
      "lat": 39.956047494309146,
      "lon": -75.18158136686509,
      "heading": "S",
      "velocity": 0,
      "lastUpdate": "2026-01-17T09:14:35-05:00",
      "nextStation": "Philadelphia 30th Street",
      "status": "Active"
    },
    {
      "trainNum": "661",
      "routeName": "Keystone",
      "lat": 40.046600787704996,
      "lon": -75.39025300846953,
      "heading": "W",
      "velocity": 71.8438034057617,
      "lastUpdate": "2026-01-17T09:15:34-05:00",
      "nextStation": "Paoli",
      "status": "Active"
    },
    {
      "trainNum": "662",
      "routeName": "Keystone",
      "lat": 39.98334925711115,
      "lon": -76.01791586085328,
      "heading": "S",
      "velocity": 56.7109031677246,
      "lastUpdate": "2026-01-17T09:15:35-05:00",
      "nextStation": "Parkesburg",
      "status": "Active"
    },
    {
      "trainNum": "664",
      "routeName": "Keystone",
      "lat": 40.261108062055214,
      "lon": -76.8782023317206,
      "heading": "N",
      "velocity": 0,
      "lastUpdate": "2026-01-17T09:15:00-05:00",
      "nextStation": "Harrisburg",
      "status": "Predeparture"
    },
    {
      "trainNum": "2201",
      "routeName": "Acela",
      "lat": 39.30780817654985,
      "lon": -76.6150687163919,
      "heading": "N",
      "velocity": 0,
      "lastUpdate": "2026-01-17T09:15:33-05:00",
      "nextStation": "Baltimore Penn",
      "status": "Active"
    },
    {
      "trainNum": "2203",
      "routeName": "Acela",
      "lat": 39.96847196533136,
      "lon": -75.19391047252493,
      "heading": "E",
      "velocity": 30.7198963165283,
      "lastUpdate": "2026-01-17T09:15:32-05:00",
      "nextStation": "Philadelphia 30th Street",
      "status": "Active"
    },
    {
      "trainNum": "2248",
      "routeName": "Acela",
      "lat": 39.74151649391417,
      "lon": -75.53370091112774,
      "heading": "NE",
      "velocity": 72.0249938964844,
      "lastUpdate": "2026-01-17T09:15:33-05:00",
      "nextStation": "Philadelphia 30th Street",
      "status": "Active"
    },
    {
      "trainNum": "2250",
      "routeName": "Acela",
      "lat": 39.29584909679071,
      "lon": -76.65172033912168,
      "heading": "N",
      "velocity": 26.3377323150635,
      "lastUpdate": "2026-01-17T09:15:33-05:00",
      "nextStation": "Baltimore Penn",
      "status": "Active"
    }
  ]
}