{
  "collected_at": "2026-01-16T11:53:24.401480+00:00",
  "source": "AISstream.io",
  "region": "Baltimore / Chesapeake Bay",
  "bbox": [
    [
      36.8,
      -76.8
    ],
    [
      39.5,
      -75.8
    ]
  ],
  "vessel_count": 40,
  "vessels": [
    {
      "mmsi": 368396250,
      "name": "ISABEL MCALLISTER",
      "lat": 39.24993666666667,
      "lon": -76.54092,
      "speed": 1.1,
      "course": 137.3,
      "heading": 111,
      "ship_type": null,
      "timestamp": "2026-01-16T11:52:55.689273+00:00"
    },
    {
      "mmsi": 538009866,
      "name": "AGIA FILOTHEI",
      "lat": 36.940079999999995,
      "lon": -76.37036666666667,
      "speed": 0.1,
      "course": 12.5,
      "heading": 358,
      "ship_type": null,
      "timestamp": "2026-01-16T11:52:56.553216+00:00"
    },
    {
      "mmsi": 367139510,
      "name": "APRIL MORAN",
      "lat": 39.256148333333336,
      "lon": -76.58398000000001,
      "speed": 2.2,
      "course": 245.4,
      "heading": 511,
      "ship_type": null,
      "timestamp": "2026-01-16T11:52:57.693318+00:00"
    },
    {
      "mmsi": 368269610,
      "name": "HOS ROSEBUD",
      "lat": 36.959651666666666,
      "lon": -76.33041499999999,
      "speed": 0,
      "course": 282.5,
      "heading": 280,
      "ship_type": null,
      "timestamp": "2026-01-16T11:52:58.737383+00:00"
    },
    {
      "mmsi": 369970478,
      "name": "YP704",
      "lat": 38.982845,
      "lon": -76.46583666666668,
      "speed": 0,
      "course": 357.9,
      "heading": 0,
      "ship_type": null,
      "timestamp": "2026-01-16T11:52:59.460375+00:00"
    },
    {
      "mmsi": 366991413,
      "name": "USNS CODY",
      "lat": 36.916916666666665,
      "lon": -76.18223333333334,
      "speed": 0,
      "course": 48,
      "heading": 94,
      "ship_type": null,
      "timestamp": "2026-01-16T11:53:02.229855+00:00"
    },
    {
      "mmsi": 368702000,
      "name": "WARSHIP",
      "lat": 36.95186833333333,
      "lon": -76.33004166666666,
      "speed": 0,
      "course": 360,
      "heading": 511,
      "ship_type": null,
      "timestamp": "2026-01-16T11:53:02.421823+00:00"
    },
    {
      "mmsi": 370350000,
      "name": "BALSA 92",
      "lat": 38.958485,
      "lon": -76.41050666666666,
      "speed": 0,
      "course": 280,
      "heading": 278,
      "ship_type": null,
      "timestamp": "2026-01-16T11:53:02.579861+00:00"
    },
    {
      "mmsi": 367523580,
      "name": "MARK MORAN",
      "lat": 39.261105,
      "lon": -76.55618333333334,
      "speed": 0,
      "course": 72,
      "heading": 511,
      "ship_type": null,
      "timestamp": "2026-01-16T11:53:03.418035+00:00"
    },
    {
      "mmsi": 563268700,
      "name": "EVER META",
      "lat": 39.24710666666667,
      "lon": -76.54026999999999,
      "speed": 1.3,
      "course": 171.8,
      "heading": 181,
      "ship_type": null,
      "timestamp": "2026-01-16T11:53:03.618923+00:00"
    },
    {
      "mmsi": 366999275,
      "name": "USACE HARRELL",
      "lat": 36.857321666666664,
      "lon": -76.30775666666666,
      "speed": 0,
      "course": 250.9,
      "heading": 511,
      "ship_type": null,
      "timestamp": "2026-01-16T11:53:03.697453+00:00"
    },
    {
      "mmsi": 366779420,
      "name": "ALERT",
      "lat": 36.865768333333335,
      "lon": -76.32389833333333,
      "speed": 3.5,
      "course": 313.8,
      "heading": 311,
      "ship_type": null,
      "timestamp": "2026-01-16T11:53:03.868908+00:00"
    },
    {
      "mmsi": 367446390,
      "name": "KAREN MORAN",
      "lat": 36.95332333333333,
      "lon": -76.32841833333333,
      "speed": 0.1,
      "course": 303.5,
      "heading": 281,
      "ship_type": null,
      "timestamp": "2026-01-16T11:53:04.303117+00:00"
    },
    {
      "mmsi": 368193180,
      "name": "INTRA RECOIL",
      "lat": 36.808308333333336,
      "lon": -76.28641999999999,
      "speed": 0,
      "course": 313.4,
      "heading": 511,
      "ship_type": null,
      "timestamp": "2026-01-16T11:53:05.732286+00:00"
    },
    {
      "mmsi": 367477980,
      "name": "OYSTER CREEK",
      "lat": 36.87137499999999,
      "lon": -76.34775166666667,
      "speed": 0,
      "course": 159,
      "heading": 166,
      "ship_type": null,
      "timestamp": "2026-01-16T11:53:06.083026+00:00"
    },
    {
      "mmsi": 367159090,
      "name": "WILLIAM E POOLE",
      "lat": 37.025126666666665,
      "lon": -76.51515833333333,
      "speed": 5.9,
      "course": 122.3,
      "heading": 121,
      "ship_type": null,
      "timestamp": "2026-01-16T11:53:06.368202+00:00"
    },
    {
      "mmsi": 367667560,
      "name": "SEA CRESCENT",
      "lat": 36.96160833333333,
      "lon": -76.409105,
      "speed": 0,
      "course": 23.5,
      "heading": 27,
      "ship_type": null,
      "timestamp": "2026-01-16T11:53:07.343580+00:00"
    },
    {
      "mmsi": 367712350,
      "name": "UNCLE MIKE",
      "lat": 36.97989166666667,
      "lon": -76.30250500000001,
      "speed": 0,
      "course": 46.5,
      "heading": 89,
      "ship_type": null,
      "timestamp": "2026-01-16T11:53:08.255689+00:00"
    },
    {
      "mmsi": 369970480,
      "name": "YP706",
      "lat": 38.984116666666665,
      "lon": -76.46738333333333,
      "speed": 0,
      "course": 339.8,
      "heading": 511,
      "ship_type": null,
      "timestamp": "2026-01-16T11:53:08.355804+00:00"
    },
    {
      "mmsi": 367029870,
      "name": "SUN COAST",
      "lat": 39.22502333333333,
      "lon": -76.57984833333333,
      "speed": 0,
      "course": 183.2,
      "heading": 331,
      "ship_type": null,
      "timestamp": "2026-01-16T11:53:08.460305+00:00"
    },
    {
      "mmsi": 368098000,
      "name": "STUYVESANT",
      "lat": 36.96941666666667,
      "lon": -76.08599166666666,
      "speed": 11.2,
      "course": 289.1,
      "heading": 285,
      "ship_type": null,
      "timestamp": "2026-01-16T11:53:10.863742+00:00"
    },
    {
      "mmsi": 247281100,
      "name": "GRANDE MAROCCO",
      "lat": 39.084785000000004,
      "lon": -76.39445500000001,
      "speed": 13.4,
      "course": 180,
      "heading": 181,
      "ship_type": null,
      "timestamp": "2026-01-16T11:53:11.590583+00:00"
    },
    {
      "mmsi": 355953000,
      "name": "SEA TREASURE",
      "lat": 37.24079,
      "lon": -76.110895,
      "speed": 0.1,
      "course": 264.5,
      "heading": 256,
      "ship_type": null,
      "timestamp": "2026-01-16T11:53:11.827800+00:00"
    },
    {
      "mmsi": 367489820,
      "name": "CAPTAIN MAC",
      "lat": 39.00695833333334,
      "lon": -76.4042,
      "speed": 0,
      "course": 360,
      "heading": 511,
      "ship_type": null,
      "timestamp": "2026-01-16T11:53:12.550984+00:00"
    },
    {
      "mmsi": 369970437,
      "name": "STILETTO",
      "lat": 36.91118666666667,
      "lon": -76.18249833333333,
      "speed": 0,
      "course": 245.2,
      "heading": 511,
      "ship_type": null,
      "timestamp": "2026-01-16T11:53:13.653888+00:00"
    },
    {
      "mmsi": 367576060,
      "name": "BRIDGET MCALLISTER",
      "lat": 39.24556833333334,
      "lon": -76.54087166666666,
      "speed": 1.3,
      "course": 183.9,
      "heading": 40,
      "ship_type": null,
      "timestamp": "2026-01-16T11:53:14.177790+00:00"
    },
    {
      "mmsi": 367341190,
      "name": "WYE RIVER",
      "lat": 39.22505666666667,
      "lon": -76.54792833333333,
      "speed": 1.2,
      "course": 127,
      "heading": 146,
      "ship_type": null,
      "timestamp": "2026-01-16T11:53:15.023339+00:00"
    },
    {
      "mmsi": 368731000,
      "name": "CG FRANK DREW",
      "lat": 39.197255000000006,
      "lon": -76.56879166666666,
      "speed": 0.1,
      "course": 199.1,
      "heading": 511,
      "ship_type": null,
      "timestamp": "2026-01-16T11:53:15.275063+00:00"
    },
    {
      "mmsi": 367083060,
      "name": "CABARET2",
      "lat": 38.967009999999995,
      "lon": -76.478185,
      "speed": 0,
      "course": 360,
      "heading": 511,
      "ship_type": null,
      "timestamp": "2026-01-16T11:53:15.456002+00:00"
    },
    {
      "mmsi": 368409350,
      "name": "OLD DOMINION",
      "lat": 36.96375833333333,
      "lon": -76.42384,
      "speed": 0.6,
      "course": 144,
      "heading": 175,
      "ship_type": null,
      "timestamp": "2026-01-16T11:53:16.430096+00:00"
    },
    {
      "mmsi": 368367030,
      "name": "THOMAS BROWN",
      "lat": 36.950205,
      "lon": -76.40503166666667,
      "speed": 7.5,
      "course": 263.3,
      "heading": 216,
      "ship_type": null,
      "timestamp": "2026-01-16T11:53:16.515137+00:00"
    },
    {
      "mmsi": 368278130,
      "name": "KIMBERLY-JO",
      "lat": 39.22371666666666,
      "lon": -76.56338000000001,
      "speed": 5.3,
      "course": 62.4,
      "heading": 511,
      "ship_type": null,
      "timestamp": "2026-01-16T11:53:17.021483+00:00"
    },
    {
      "mmsi": 367619930,
      "name": "STARSHIP 3",
      "lat": 39.27692833333333,
      "lon": -76.58098666666666,
      "speed": 0,
      "course": 360,
      "heading": 511,
      "ship_type": null,
      "timestamp": "2026-01-16T11:53:17.084034+00:00"
    },
    {
      "mmsi": 311321000,
      "name": "VISION OF THE SEAS",
      "lat": 39.255446666666664,
      "lon": -76.58566833333333,
      "speed": 4.6,
      "course": 278,
      "heading": 272,
      "ship_type": null,
      "timestamp": "2026-01-16T11:53:18.686616+00:00"
    },
    {
      "mmsi": 369970039,
      "name": "YP703",
      "lat": 38.98430833333334,
      "lon": -76.467015,
      "speed": 0,
      "course": 189.4,
      "heading": 104,
      "ship_type": null,
      "timestamp": "2026-01-16T11:53:19.466791+00:00"
    },
    {
      "mmsi": 369970481,
      "name": "YP707",
      "lat": 38.983848333333334,
      "lon": -76.467515,
      "speed": 0,
      "course": 327,
      "heading": 349,
      "ship_type": null,
      "timestamp": "2026-01-16T11:53:19.527018+00:00"
    },
    {
      "mmsi": 338238172,
      "name": "OHANA",
      "lat": 38.902834999999996,
      "lon": -76.50929,
      "speed": 0,
      "course": 258.8,
      "heading": 511,
      "ship_type": null,
      "timestamp": "2026-01-16T11:53:21.484583+00:00"
    },
    {
      "mmsi": 373874000,
      "name": "KEY FUTURE",
      "lat": 38.89017,
      "lon": -76.39568666666668,
      "speed": 11.4,
      "course": 187,
      "heading": 186,
      "ship_type": null,
      "timestamp": "2026-01-16T11:53:22.492006+00:00"
    },
    {
      "mmsi": 368857000,
      "name": "CG MAPLE",
      "lat": 39.19798333333333,
      "lon": -76.56938333333332,
      "speed": 0.1,
      "course": 8.7,
      "heading": 511,
      "ship_type": null,
      "timestamp": "2026-01-16T11:53:23.169746+00:00"
    },
    {
      "mmsi": 354114000,
      "name": "ENERGY UNIVERSE",
      "lat": 38.389649999999996,
      "lon": -76.36674500000001,
      "speed": 3.4,
      "course": 321.1,
      "heading": 321,
      "ship_type": null,
      "timestamp": "2026-01-16T11:53:23.179882+00:00"
    }
  ]
}