{
  "collected_at": "2026-01-15T08:57:08.899637+00:00",
  "source": "AISstream.io",
  "region": "Baltimore / Chesapeake Bay",
  "bbox": [
    [
      36.8,
      -76.8
    ],
    [
      39.5,
      -75.8
    ]
  ],
  "vessel_count": 31,
  "vessels": [
    {
      "mmsi": 367029960,
      "name": "CALUSA COAST",
      "lat": 36.948483333333336,
      "lon": -76.35898,
      "speed": 0.2,
      "course": 184.4,
      "heading": 46,
      "ship_type": null,
      "timestamp": "2026-01-15T08:56:39.852582+00:00"
    },
    {
      "mmsi": 563268700,
      "name": "EVER META",
      "lat": 38.89866,
      "lon": -76.392455,
      "speed": 14.1,
      "course": 7,
      "heading": 4,
      "ship_type": null,
      "timestamp": "2026-01-15T08:56:51.945832+00:00"
    },
    {
      "mmsi": 338238172,
      "name": "OHANA",
      "lat": 38.90285166666667,
      "lon": -76.509305,
      "speed": 0,
      "course": 196,
      "heading": 511,
      "ship_type": null,
      "timestamp": "2026-01-15T08:57:01.052659+00:00"
    },
    {
      "mmsi": 367185680,
      "name": "EAST COAST",
      "lat": 39.24975833333333,
      "lon": -76.5544,
      "speed": 0.1,
      "course": 17,
      "heading": 293,
      "ship_type": null,
      "timestamp": "2026-01-15T08:56:41.074357+00:00"
    },
    {
      "mmsi": 235008930,
      "name": "VOE VIKING",
      "lat": 36.86759666666667,
      "lon": -76.31674,
      "speed": 0,
      "course": 360,
      "heading": 511,
      "ship_type": null,
      "timestamp": "2026-01-15T08:56:41.784070+00:00"
    },
    {
      "mmsi": 368312320,
      "name": "JANE MCALLISTER",
      "lat": 36.93093833333333,
      "lon": -76.33353833333334,
      "speed": 0.1,
      "course": 307.6,
      "heading": 171,
      "ship_type": null,
      "timestamp": "2026-01-15T08:56:42.031225+00:00"
    },
    {
      "mmsi": 366837130,
      "name": "SUSAN MORAN",
      "lat": 36.95309833333333,
      "lon": -76.32797333333333,
      "speed": 0,
      "course": 306.7,
      "heading": 98,
      "ship_type": null,
      "timestamp": "2026-01-15T08:56:42.104134+00:00"
    },
    {
      "mmsi": 368702000,
      "name": "WARSHIP",
      "lat": 36.95185,
      "lon": -76.32996833333333,
      "speed": 0,
      "course": 360,
      "heading": 511,
      "ship_type": null,
      "timestamp": "2026-01-15T08:56:42.152614+00:00"
    },
    {
      "mmsi": 366962220,
      "name": "BART L",
      "lat": 36.99994166666667,
      "lon": -76.29330833333333,
      "speed": 9.5,
      "course": 58.1,
      "heading": 511,
      "ship_type": null,
      "timestamp": "2026-01-15T08:56:43.874194+00:00"
    },
    {
      "mmsi": 367082130,
      "name": "TIMOTHY MCALLISTER",
      "lat": 36.96955166666667,
      "lon": -76.43092,
      "speed": 0,
      "course": 316,
      "heading": 249,
      "ship_type": null,
      "timestamp": "2026-01-15T08:56:44.247054+00:00"
    },
    {
      "mmsi": 367446390,
      "name": "KAREN MORAN",
      "lat": 36.95332833333334,
      "lon": -76.32841666666667,
      "speed": 0,
      "course": 139.4,
      "heading": 277,
      "ship_type": null,
      "timestamp": "2026-01-15T08:56:44.721871+00:00"
    },
    {
      "mmsi": 367323010,
      "name": "PATRICIA MORAN",
      "lat": 36.952684999999995,
      "lon": -76.32818166666667,
      "speed": 0,
      "course": 350.3,
      "heading": 511,
      "ship_type": null,
      "timestamp": "2026-01-15T08:56:45.181797+00:00"
    },
    {
      "mmsi": 367083060,
      "name": "CABARET2",
      "lat": 38.96700666666666,
      "lon": -76.47818000000001,
      "speed": 0,
      "course": 0,
      "heading": 0,
      "ship_type": null,
      "timestamp": "2026-01-15T08:56:55.873022+00:00"
    },
    {
      "mmsi": 357114000,
      "name": "JAL MURARI",
      "lat": 37.212536666666665,
      "lon": -76.116875,
      "speed": 0.1,
      "course": 338.7,
      "heading": 212,
      "ship_type": null,
      "timestamp": "2026-01-15T08:56:46.251270+00:00"
    },
    {
      "mmsi": 366966210,
      "name": "MCALLISTER SISTERS",
      "lat": 39.23893833333333,
      "lon": -76.237455,
      "speed": 6.4,
      "course": 191,
      "heading": 193,
      "ship_type": null,
      "timestamp": "2026-01-15T08:56:46.344715+00:00"
    },
    {
      "mmsi": 368155390,
      "name": "INTRA REBEL",
      "lat": 39.204748333333335,
      "lon": -76.58233333333332,
      "speed": 0,
      "course": 159.3,
      "heading": 258,
      "ship_type": null,
      "timestamp": "2026-01-15T08:56:46.517636+00:00"
    },
    {
      "mmsi": 368441690,
      "name": "FEDERAL HILL",
      "lat": 39.25577333333333,
      "lon": -76.53495666666666,
      "speed": 0,
      "course": 64.8,
      "heading": 297,
      "ship_type": null,
      "timestamp": "2026-01-15T08:56:57.953574+00:00"
    },
    {
      "mmsi": 367834000,
      "name": "GARY I GORDON",
      "lat": 39.269065,
      "lon": -76.57092333333334,
      "speed": 0,
      "course": 0,
      "heading": 267,
      "ship_type": null,
      "timestamp": "2026-01-15T08:56:49.201610+00:00"
    },
    {
      "mmsi": 367029690,
      "name": "IVORY COAST",
      "lat": 39.26467666666667,
      "lon": -76.57192,
      "speed": 0,
      "course": 292.5,
      "heading": 85,
      "ship_type": null,
      "timestamp": "2026-01-15T08:56:53.308938+00:00"
    },
    {
      "mmsi": 366828620,
      "name": "VICKI M MCALLISTER",
      "lat": 39.27025833333333,
      "lon": -76.57985833333333,
      "speed": 2.1,
      "course": 96.8,
      "heading": 511,
      "ship_type": null,
      "timestamp": "2026-01-15T08:56:53.319952+00:00"
    },
    {
      "mmsi": 369970482,
      "name": "YP708",
      "lat": 38.98409166666667,
      "lon": -76.46755166666667,
      "speed": 0,
      "course": 13.4,
      "heading": 511,
      "ship_type": null,
      "timestamp": "2026-01-15T08:56:56.514725+00:00"
    },
    {
      "mmsi": 636022859,
      "name": "LADY J",
      "lat": 36.96251666666667,
      "lon": -76.42356333333333,
      "speed": 0,
      "course": 287.2,
      "heading": 39,
      "ship_type": null,
      "timestamp": "2026-01-15T08:56:56.639046+00:00"
    },
    {
      "mmsi": 636093100,
      "name": "SUAPE EXPRESS",
      "lat": 36.98611833333334,
      "lon": -76.15614333333333,
      "speed": 15.8,
      "course": 287.1,
      "heading": 287,
      "ship_type": null,
      "timestamp": "2026-01-15T08:56:57.111056+00:00"
    },
    {
      "mmsi": 369970480,
      "name": "YP706",
      "lat": 38.984114999999996,
      "lon": -76.46738166666667,
      "speed": 0,
      "course": 325,
      "heading": 325,
      "ship_type": null,
      "timestamp": "2026-01-15T08:56:57.525129+00:00"
    },
    {
      "mmsi": 369970481,
      "name": "YP707",
      "lat": 38.983865,
      "lon": -76.4675,
      "speed": 0,
      "course": 353,
      "heading": 348,
      "ship_type": null,
      "timestamp": "2026-01-15T08:56:58.479033+00:00"
    },
    {
      "mmsi": 366999646,
      "name": "USCGC SLEDGE",
      "lat": 39.22946833333333,
      "lon": -76.55976666666668,
      "speed": 0.1,
      "course": 139.5,
      "heading": 286,
      "ship_type": null,
      "timestamp": "2026-01-15T08:57:00.680819+00:00"
    },
    {
      "mmsi": 370350000,
      "name": "BALSA 92",
      "lat": 38.95829166666667,
      "lon": -76.41045000000001,
      "speed": 0.1,
      "course": 162.5,
      "heading": 292,
      "ship_type": null,
      "timestamp": "2026-01-15T08:57:02.607726+00:00"
    },
    {
      "mmsi": 368409350,
      "name": "OLD DOMINION",
      "lat": 36.95792666666667,
      "lon": -76.39999333333334,
      "speed": 27.3,
      "course": 277.6,
      "heading": 277,
      "ship_type": null,
      "timestamp": "2026-01-15T08:57:05.344076+00:00"
    },
    {
      "mmsi": 368169560,
      "name": "ATLANTIC ENDEAVOR",
      "lat": 36.92288333333333,
      "lon": -76.18809333333334,
      "speed": 0,
      "course": 342.1,
      "heading": 105,
      "ship_type": null,
      "timestamp": "2026-01-15T08:57:08.049162+00:00"
    },
    {
      "mmsi": 368269610,
      "name": "HOS ROSEBUD",
      "lat": 36.92020333333333,
      "lon": -76.18238166666667,
      "speed": 0,
      "course": 234.5,
      "heading": 273,
      "ship_type": null,
      "timestamp": "2026-01-15T08:57:08.735871+00:00"
    },
    {
      "mmsi": 367769180,
      "name": "CLAYTON W MORAN",
      "lat": 36.954193333333336,
      "lon": -76.34484333333333,
      "speed": 12.6,
      "course": 287.9,
      "heading": 285,
      "ship_type": null,
      "timestamp": "2026-01-15T08:57:08.777811+00:00"
    }
  ]
}