{
  "collected_at": "2026-01-16T19:41:29.816833+00:00",
  "source": "AISstream.io",
  "region": "Baltimore / Chesapeake Bay",
  "bbox": [
    [
      36.8,
      -76.8
    ],
    [
      39.5,
      -75.8
    ]
  ],
  "vessel_count": 29,
  "vessels": [
    {
      "mmsi": 367341190,
      "name": "WYE RIVER",
      "lat": 39.24348333333333,
      "lon": -76.57032333333333,
      "speed": 0,
      "course": 29.9,
      "heading": 79,
      "ship_type": null,
      "timestamp": "2026-01-16T19:41:00.826370+00:00"
    },
    {
      "mmsi": 366991413,
      "name": "USNS CODY",
      "lat": 36.916916666666665,
      "lon": -76.18223333333334,
      "speed": 0,
      "course": 47.5,
      "heading": 93,
      "ship_type": null,
      "timestamp": "2026-01-16T19:41:02.323901+00:00"
    },
    {
      "mmsi": 368702000,
      "name": "WARSHIP",
      "lat": 36.951879999999996,
      "lon": -76.32993333333334,
      "speed": 0,
      "course": 360,
      "heading": 511,
      "ship_type": null,
      "timestamp": "2026-01-16T19:41:13.612410+00:00"
    },
    {
      "mmsi": 373342000,
      "name": "NEW WAVELET",
      "lat": 38.93306166666667,
      "lon": -76.39706500000001,
      "speed": 13.4,
      "course": 7,
      "heading": 5,
      "ship_type": null,
      "timestamp": "2026-01-16T19:41:13.256135+00:00"
    },
    {
      "mmsi": 368226870,
      "name": "SEAWARD  21",
      "lat": 36.98315,
      "lon": -76.30517333333334,
      "speed": 4.9,
      "course": 192.3,
      "heading": 511,
      "ship_type": null,
      "timestamp": "2026-01-16T19:41:04.986009+00:00"
    },
    {
      "mmsi": 367576060,
      "name": "BRIDGET MCALLISTER",
      "lat": 39.268971666666665,
      "lon": -76.58085166666666,
      "speed": 0,
      "course": 52.8,
      "heading": 205,
      "ship_type": null,
      "timestamp": "2026-01-16T19:41:05.286804+00:00"
    },
    {
      "mmsi": 563289100,
      "name": "COSCO FAITH",
      "lat": 36.879016666666665,
      "lon": -76.35041,
      "speed": 0.1,
      "course": 157.3,
      "heading": 347,
      "ship_type": null,
      "timestamp": "2026-01-16T19:41:06.502303+00:00"
    },
    {
      "mmsi": 368396250,
      "name": "ISABEL MCALLISTER",
      "lat": 39.25611333333333,
      "lon": -76.57902,
      "speed": 10.4,
      "course": 267.7,
      "heading": 266,
      "ship_type": null,
      "timestamp": "2026-01-16T19:41:07.044310+00:00"
    },
    {
      "mmsi": 368371930,
      "name": "OCEANUS VI",
      "lat": 37.016475,
      "lon": -76.13435,
      "speed": 6.3,
      "course": 206.3,
      "heading": 214,
      "ship_type": null,
      "timestamp": "2026-01-16T19:41:09.735122+00:00"
    },
    {
      "mmsi": 366828620,
      "name": "VICKI M MCALLISTER",
      "lat": 39.26871666666667,
      "lon": -76.58100833333333,
      "speed": 0,
      "course": 263.8,
      "heading": 511,
      "ship_type": null,
      "timestamp": "2026-01-16T19:41:12.773005+00:00"
    },
    {
      "mmsi": 367523580,
      "name": "MARK MORAN",
      "lat": 39.26104,
      "lon": -76.55619166666666,
      "speed": 0,
      "course": 265.1,
      "heading": 511,
      "ship_type": null,
      "timestamp": "2026-01-16T19:41:13.680127+00:00"
    },
    {
      "mmsi": 366980000,
      "name": "WARSHIP 67",
      "lat": 36.94112666666667,
      "lon": -76.33040166666666,
      "speed": 0,
      "course": 360,
      "heading": 511,
      "ship_type": null,
      "timestamp": "2026-01-16T19:41:14.033065+00:00"
    },
    {
      "mmsi": 367619930,
      "name": "STARSHIP 3",
      "lat": 39.27692166666667,
      "lon": -76.58101666666667,
      "speed": 0,
      "course": 360,
      "heading": 511,
      "ship_type": null,
      "timestamp": "2026-01-16T19:41:15.379145+00:00"
    },
    {
      "mmsi": 366878280,
      "name": "PILOT BOAT PATAPSCO",
      "lat": 38.965934999999995,
      "lon": -76.47874,
      "speed": 0.1,
      "course": 180.7,
      "heading": 511,
      "ship_type": null,
      "timestamp": "2026-01-16T19:41:15.459571+00:00"
    },
    {
      "mmsi": 368731000,
      "name": "CG FRANK DREW",
      "lat": 39.197251666666666,
      "lon": -76.56878666666667,
      "speed": 0,
      "course": 0,
      "heading": 511,
      "ship_type": null,
      "timestamp": "2026-01-16T19:41:16.015873+00:00"
    },
    {
      "mmsi": 367932000,
      "name": "JOHN LENTHALL",
      "lat": 36.93815166666666,
      "lon": -76.338225,
      "speed": 10.8,
      "course": 3.9,
      "heading": 2,
      "ship_type": null,
      "timestamp": "2026-01-16T19:41:16.962057+00:00"
    },
    {
      "mmsi": 538011780,
      "name": "ALEXANDRIA",
      "lat": 36.962875000000004,
      "lon": -76.42423166666667,
      "speed": 0,
      "course": 139.3,
      "heading": 38,
      "ship_type": null,
      "timestamp": "2026-01-16T19:41:17.174470+00:00"
    },
    {
      "mmsi": 368926258,
      "name": "CATLETT",
      "lat": 39.26697166666667,
      "lon": -76.57950833333332,
      "speed": 0,
      "course": 228.9,
      "heading": 511,
      "ship_type": null,
      "timestamp": "2026-01-16T19:41:17.313229+00:00"
    },
    {
      "mmsi": 368277530,
      "name": "MISS MADELINE",
      "lat": 39.21460166666667,
      "lon": -76.53012,
      "speed": 0,
      "course": 306.3,
      "heading": 52,
      "ship_type": null,
      "timestamp": "2026-01-16T19:41:18.657554+00:00"
    },
    {
      "mmsi": 367712350,
      "name": "UNCLE MIKE",
      "lat": 36.962895,
      "lon": -76.2957,
      "speed": 0,
      "course": 278.7,
      "heading": 225,
      "ship_type": null,
      "timestamp": "2026-01-16T19:41:18.693783+00:00"
    },
    {
      "mmsi": 303829003,
      "name": "TSV-5 VINDICATOR",
      "lat": 36.9161,
      "lon": -76.18209166666666,
      "speed": 0,
      "course": 359.7,
      "heading": 99,
      "ship_type": null,
      "timestamp": "2026-01-16T19:41:19.031615+00:00"
    },
    {
      "mmsi": 367384520,
      "name": "ANNE JARRETT",
      "lat": 36.909641666666666,
      "lon": -76.32726,
      "speed": 0,
      "course": 350.8,
      "heading": 163,
      "ship_type": null,
      "timestamp": "2026-01-16T19:41:19.035331+00:00"
    },
    {
      "mmsi": 367696380,
      "name": "VIRGINIA WAVE",
      "lat": 36.966141666666665,
      "lon": -76.41306833333333,
      "speed": 0,
      "course": 187.3,
      "heading": 160,
      "ship_type": null,
      "timestamp": "2026-01-16T19:41:19.355167+00:00"
    },
    {
      "mmsi": 338238172,
      "name": "OHANA",
      "lat": 38.902855,
      "lon": -76.50929500000001,
      "speed": 0,
      "course": 237,
      "heading": 237,
      "ship_type": null,
      "timestamp": "2026-01-16T19:41:20.859981+00:00"
    },
    {
      "mmsi": 338060011,
      "name": "CAPT. KENNETH",
      "lat": 39.24792,
      "lon": -76.53867333333332,
      "speed": 0.1,
      "course": 360,
      "heading": 511,
      "ship_type": null,
      "timestamp": "2026-01-16T19:41:20.889649+00:00"
    },
    {
      "mmsi": 369970039,
      "name": "YP703",
      "lat": 38.98427166666667,
      "lon": -76.46702166666667,
      "speed": 0,
      "course": 189,
      "heading": 103,
      "ship_type": null,
      "timestamp": "2026-01-16T19:41:22.112254+00:00"
    },
    {
      "mmsi": 368376830,
      "name": "ROARING POINT",
      "lat": 36.81654,
      "lon": -76.29086666666667,
      "speed": 7.4,
      "course": 4.9,
      "heading": 2,
      "ship_type": null,
      "timestamp": "2026-01-16T19:41:26.294032+00:00"
    },
    {
      "mmsi": 367031390,
      "name": "CAPTAIN HANK",
      "lat": 39.152699999999996,
      "lon": -76.3154,
      "speed": 9.5,
      "course": 12.4,
      "heading": 10,
      "ship_type": null,
      "timestamp": "2026-01-16T19:41:28.986011+00:00"
    },
    {
      "mmsi": 369970478,
      "name": "YP704",
      "lat": 38.982841666666666,
      "lon": -76.46582666666667,
      "speed": 0,
      "course": 169,
      "heading": 169,
      "ship_type": null,
      "timestamp": "2026-01-16T19:41:29.412536+00:00"
    }
  ]
}