{
  "collected_at": "2026-01-17T08:48:29.982027+00:00",
  "source": "AISstream.io",
  "region": "Baltimore / Chesapeake Bay",
  "bbox": [
    [
      36.8,
      -76.8
    ],
    [
      39.5,
      -75.8
    ]
  ],
  "vessel_count": 24,
  "vessels": [
    {
      "mmsi": 368312320,
      "name": "JANE MCALLISTER",
      "lat": 36.95697666666667,
      "lon": -76.37833666666667,
      "speed": 9.6,
      "course": 265,
      "heading": 261,
      "ship_type": null,
      "timestamp": "2026-01-17T08:48:01.986952+00:00"
    },
    {
      "mmsi": 373342000,
      "name": "NEW WAVELET",
      "lat": 39.22176666666667,
      "lon": -76.57665666666666,
      "speed": 0,
      "course": 242.1,
      "heading": 274,
      "ship_type": null,
      "timestamp": "2026-01-17T08:48:08.522602+00:00"
    },
    {
      "mmsi": 367093970,
      "name": "CAPT STEVE",
      "lat": 39.208975,
      "lon": -76.58287,
      "speed": 0,
      "course": 185.1,
      "heading": 511,
      "ship_type": null,
      "timestamp": "2026-01-17T08:48:09.989880+00:00"
    },
    {
      "mmsi": 354114000,
      "name": "ENERGY UNIVERSE",
      "lat": 38.40392166666666,
      "lon": -76.38470166666666,
      "speed": 0,
      "course": 184.9,
      "heading": 325,
      "ship_type": null,
      "timestamp": "2026-01-17T08:48:10.752976+00:00"
    },
    {
      "mmsi": 368006020,
      "name": "ROSEMARY MCALLISTER",
      "lat": 36.95455833333333,
      "lon": -76.40138833333334,
      "speed": 10.7,
      "course": 265.8,
      "heading": 266,
      "ship_type": null,
      "timestamp": "2026-01-17T08:48:13.349785+00:00"
    },
    {
      "mmsi": 367462360,
      "name": "CINDY R",
      "lat": 36.85886333333334,
      "lon": -76.347,
      "speed": 0,
      "course": 360,
      "heading": 511,
      "ship_type": null,
      "timestamp": "2026-01-17T08:48:13.980808+00:00"
    },
    {
      "mmsi": 368172430,
      "name": "STEPHEN J LEAMAN",
      "lat": 36.91620666666667,
      "lon": -76.338065,
      "speed": 4.6,
      "course": 115.9,
      "heading": 97,
      "ship_type": null,
      "timestamp": "2026-01-17T08:48:14.488948+00:00"
    },
    {
      "mmsi": 369970482,
      "name": "YP708",
      "lat": 38.98406166666667,
      "lon": -76.46755499999999,
      "speed": 0,
      "course": 26,
      "heading": 26,
      "ship_type": null,
      "timestamp": "2026-01-17T08:48:14.791416+00:00"
    },
    {
      "mmsi": 367308110,
      "name": "THE HUNTER",
      "lat": 39.26833833333333,
      "lon": -76.58116833333334,
      "speed": 0,
      "course": 264.3,
      "heading": 511,
      "ship_type": null,
      "timestamp": "2026-01-17T08:48:17.165062+00:00"
    },
    {
      "mmsi": 311001144,
      "name": "UNITY MOON",
      "lat": 39.267005000000005,
      "lon": -76.57226833333334,
      "speed": 0,
      "course": 44.3,
      "heading": 88,
      "ship_type": null,
      "timestamp": "2026-01-17T08:48:18.796901+00:00"
    },
    {
      "mmsi": 368707000,
      "name": "GEORGE WATSON",
      "lat": 39.267835,
      "lon": -76.57029833333333,
      "speed": 0,
      "course": 0,
      "heading": 268,
      "ship_type": null,
      "timestamp": "2026-01-17T08:48:19.297988+00:00"
    },
    {
      "mmsi": 368926087,
      "name": "WARSHIP 4",
      "lat": 36.96266666666667,
      "lon": -76.42,
      "speed": 0,
      "course": 0,
      "heading": 511,
      "ship_type": null,
      "timestamp": "2026-01-17T08:48:19.458852+00:00"
    },
    {
      "mmsi": 368013860,
      "name": "PAUL CANDIES",
      "lat": 36.952284999999996,
      "lon": -76.42237166666668,
      "speed": 0,
      "course": 81.9,
      "heading": 299,
      "ship_type": null,
      "timestamp": "2026-01-17T08:48:20.191677+00:00"
    },
    {
      "mmsi": 367866000,
      "name": "LEROY GRUMMAN",
      "lat": 36.959224999999996,
      "lon": -76.327585,
      "speed": 0,
      "course": 42.8,
      "heading": 278,
      "ship_type": null,
      "timestamp": "2026-01-17T08:48:21.408678+00:00"
    },
    {
      "mmsi": 368702000,
      "name": "WARSHIP",
      "lat": 36.951845000000006,
      "lon": -76.32996666666666,
      "speed": 0,
      "course": 360,
      "heading": 511,
      "ship_type": null,
      "timestamp": "2026-01-17T08:48:22.149096+00:00"
    },
    {
      "mmsi": 367376440,
      "name": "LONG ISLAND",
      "lat": 39.243425,
      "lon": -76.57072833333334,
      "speed": 0,
      "course": 291.5,
      "heading": 511,
      "ship_type": null,
      "timestamp": "2026-01-17T08:48:22.545958+00:00"
    },
    {
      "mmsi": 368441690,
      "name": "FEDERAL HILL",
      "lat": 39.25577166666667,
      "lon": -76.53493499999999,
      "speed": 0,
      "course": 332.2,
      "heading": 296,
      "ship_type": null,
      "timestamp": "2026-01-17T08:48:23.215745+00:00"
    },
    {
      "mmsi": 370350000,
      "name": "BALSA 92",
      "lat": 38.959865,
      "lon": -76.411335,
      "speed": 0,
      "course": 115,
      "heading": 201,
      "ship_type": null,
      "timestamp": "2026-01-17T08:48:23.276364+00:00"
    },
    {
      "mmsi": 366081080,
      "name": "ZEUS",
      "lat": 39.24364166666667,
      "lon": -76.56889500000001,
      "speed": 0,
      "course": 218.9,
      "heading": 259,
      "ship_type": null,
      "timestamp": "2026-01-17T08:48:24.313905+00:00"
    },
    {
      "mmsi": 368396250,
      "name": "ISABEL MCALLISTER",
      "lat": 39.269265000000004,
      "lon": -76.58075666666667,
      "speed": 0,
      "course": 308.8,
      "heading": 205,
      "ship_type": null,
      "timestamp": "2026-01-17T08:48:26.370033+00:00"
    },
    {
      "mmsi": 367852000,
      "name": "WILLIAM MCLEAN",
      "lat": 36.94930333333333,
      "lon": -76.330015,
      "speed": 0,
      "course": 174,
      "heading": 280,
      "ship_type": null,
      "timestamp": "2026-01-17T08:48:27.355553+00:00"
    },
    {
      "mmsi": 368926258,
      "name": "CATLETT",
      "lat": 39.266955,
      "lon": -76.57955833333334,
      "speed": 0,
      "course": 195.5,
      "heading": 511,
      "ship_type": null,
      "timestamp": "2026-01-17T08:48:27.432062+00:00"
    },
    {
      "mmsi": 369970478,
      "name": "YP704",
      "lat": 38.98287166666667,
      "lon": -76.46583000000001,
      "speed": 0,
      "course": 28,
      "heading": 28,
      "ship_type": null,
      "timestamp": "2026-01-17T08:48:28.372864+00:00"
    },
    {
      "mmsi": 367139510,
      "name": "APRIL MORAN",
      "lat": 39.26041333333333,
      "lon": -76.556165,
      "speed": 0,
      "course": 279.5,
      "heading": 511,
      "ship_type": null,
      "timestamp": "2026-01-17T08:48:29.060249+00:00"
    }
  ]
}