{
  "collected_at": "2026-01-17T20:53:55.792398+00:00",
  "source": "AISstream.io",
  "region": "Baltimore / Chesapeake Bay",
  "bbox": [
    [
      36.8,
      -76.8
    ],
    [
      39.5,
      -75.8
    ]
  ],
  "vessel_count": 35,
  "vessels": [
    {
      "mmsi": 368926258,
      "name": "CATLETT",
      "lat": 39.266975,
      "lon": -76.57952166666668,
      "speed": 0,
      "course": 251.8,
      "heading": 511,
      "ship_type": null,
      "timestamp": "2026-01-17T20:53:26.879866+00:00"
    },
    {
      "mmsi": 367139510,
      "name": "APRIL MORAN",
      "lat": 39.260443333333335,
      "lon": -76.55613166666667,
      "speed": 0,
      "course": 301.1,
      "heading": 511,
      "ship_type": null,
      "timestamp": "2026-01-17T20:53:27.876420+00:00"
    },
    {
      "mmsi": 367087140,
      "name": "GLENN EDWARDS",
      "lat": 36.93654333333333,
      "lon": -76.03256833333333,
      "speed": 0,
      "course": 42.4,
      "heading": 81,
      "ship_type": null,
      "timestamp": "2026-01-17T20:53:27.969142+00:00"
    },
    {
      "mmsi": 368269610,
      "name": "HOS ROSEBUD",
      "lat": 36.959645,
      "lon": -76.33041833333333,
      "speed": 0,
      "course": 282.5,
      "heading": 280,
      "ship_type": null,
      "timestamp": "2026-01-17T20:53:37.837132+00:00"
    },
    {
      "mmsi": 367819000,
      "name": "WILLIAM A. SODERMAN",
      "lat": 36.86599833333333,
      "lon": -76.31588833333333,
      "speed": 0,
      "course": 338.7,
      "heading": 229,
      "ship_type": null,
      "timestamp": "2026-01-17T20:53:28.885602+00:00"
    },
    {
      "mmsi": 367031390,
      "name": "CAPTAIN HANK",
      "lat": 38.80876666666666,
      "lon": -76.44936666666668,
      "speed": 6.8,
      "course": 195.6,
      "heading": 195,
      "ship_type": null,
      "timestamp": "2026-01-17T20:53:29.210051+00:00"
    },
    {
      "mmsi": 368098000,
      "name": "STUYVESANT",
      "lat": 37.00396333333333,
      "lon": -76.28305666666667,
      "speed": 5.1,
      "course": 268.1,
      "heading": 263,
      "ship_type": null,
      "timestamp": "2026-01-17T20:53:29.888580+00:00"
    },
    {
      "mmsi": 338238172,
      "name": "OHANA",
      "lat": 38.90284166666667,
      "lon": -76.50931666666666,
      "speed": 0,
      "course": 248.2,
      "heading": 511,
      "ship_type": null,
      "timestamp": "2026-01-17T20:53:32.162048+00:00"
    },
    {
      "mmsi": 367159090,
      "name": "WILLIAM E POOLE",
      "lat": 36.995045,
      "lon": -76.35603166666667,
      "speed": 0,
      "course": 316,
      "heading": 222,
      "ship_type": null,
      "timestamp": "2026-01-17T20:53:32.610816+00:00"
    },
    {
      "mmsi": 367165450,
      "name": "TREASURE COAST",
      "lat": 39.20876833333333,
      "lon": -76.461205,
      "speed": 0,
      "course": 206.6,
      "heading": 357,
      "ship_type": null,
      "timestamp": "2026-01-17T20:53:52.961173+00:00"
    },
    {
      "mmsi": 368006020,
      "name": "ROSEMARY MCALLISTER",
      "lat": 37.00565666666667,
      "lon": -76.27854166666665,
      "speed": 10.4,
      "course": 244.2,
      "heading": 244,
      "ship_type": null,
      "timestamp": "2026-01-17T20:53:35.716699+00:00"
    },
    {
      "mmsi": 369970482,
      "name": "YP708",
      "lat": 38.98398666666667,
      "lon": -76.46755166666667,
      "speed": 0,
      "course": 125,
      "heading": 125,
      "ship_type": null,
      "timestamp": "2026-01-17T20:53:35.752663+00:00"
    },
    {
      "mmsi": 440072000,
      "name": "CY INTEROCEAN I",
      "lat": 36.85800666666667,
      "lon": -76.32150333333334,
      "speed": 0,
      "course": 124.2,
      "heading": 83,
      "ship_type": null,
      "timestamp": "2026-01-17T20:53:35.876023+00:00"
    },
    {
      "mmsi": 366926050,
      "name": "RV SPERRY STAR III",
      "lat": 38.979101666666665,
      "lon": -76.33267000000001,
      "speed": 0.1,
      "course": 181.5,
      "heading": 511,
      "ship_type": null,
      "timestamp": "2026-01-17T20:53:36.791093+00:00"
    },
    {
      "mmsi": 369970480,
      "name": "YP706",
      "lat": 38.98418166666667,
      "lon": -76.467345,
      "speed": 0,
      "course": 111,
      "heading": 111,
      "ship_type": null,
      "timestamp": "2026-01-17T20:53:36.991469+00:00"
    },
    {
      "mmsi": 303615000,
      "name": "PRIDE OF BALTIMORE 2",
      "lat": 39.269645,
      "lon": -76.56952,
      "speed": 0,
      "course": 320.7,
      "heading": 74,
      "ship_type": null,
      "timestamp": "2026-01-17T20:53:38.443929+00:00"
    },
    {
      "mmsi": 235090599,
      "name": "VOE EARL",
      "lat": 36.86420666666667,
      "lon": -76.31484999999999,
      "speed": 0,
      "course": 96.2,
      "heading": 51,
      "ship_type": null,
      "timestamp": "2026-01-17T20:53:39.547274+00:00"
    },
    {
      "mmsi": 366782000,
      "name": "CHESAPEAKE COAST",
      "lat": 36.986365,
      "lon": -76.450675,
      "speed": 7.7,
      "course": 326.1,
      "heading": 324,
      "ship_type": null,
      "timestamp": "2026-01-17T20:53:39.778490+00:00"
    },
    {
      "mmsi": 369970481,
      "name": "YP707",
      "lat": 38.983848333333334,
      "lon": -76.4675,
      "speed": 0,
      "course": 327,
      "heading": 349,
      "ship_type": null,
      "timestamp": "2026-01-17T20:53:39.808895+00:00"
    },
    {
      "mmsi": 366878280,
      "name": "PILOT BOAT PATAPSCO",
      "lat": 38.965945000000005,
      "lon": -76.47873166666666,
      "speed": 0,
      "course": 176,
      "heading": 176,
      "ship_type": null,
      "timestamp": "2026-01-17T20:53:39.813754+00:00"
    },
    {
      "mmsi": 370350000,
      "name": "BALSA 92",
      "lat": 38.959918333333334,
      "lon": -76.41169,
      "speed": 0,
      "course": 135.3,
      "heading": 189,
      "ship_type": null,
      "timestamp": "2026-01-17T20:53:52.220931+00:00"
    },
    {
      "mmsi": 368242090,
      "name": "GALE",
      "lat": 39.21918333333333,
      "lon": -76.57605,
      "speed": 5.2,
      "course": 239.2,
      "heading": 511,
      "ship_type": null,
      "timestamp": "2026-01-17T20:53:42.441517+00:00"
    },
    {
      "mmsi": 368702000,
      "name": "WARSHIP",
      "lat": 36.95188666666666,
      "lon": -76.33000666666666,
      "speed": 0,
      "course": 360,
      "heading": 511,
      "ship_type": null,
      "timestamp": "2026-01-17T20:53:42.770909+00:00"
    },
    {
      "mmsi": 368277530,
      "name": "MISS MADELINE",
      "lat": 39.22123166666667,
      "lon": -76.53850333333334,
      "speed": 8.3,
      "course": 283.5,
      "heading": 284,
      "ship_type": null,
      "timestamp": "2026-01-17T20:53:44.168963+00:00"
    },
    {
      "mmsi": 235008930,
      "name": "VOE VIKING",
      "lat": 36.86428333333333,
      "lon": -76.31492666666666,
      "speed": 0,
      "course": 360,
      "heading": 511,
      "ship_type": null,
      "timestamp": "2026-01-17T20:53:44.341876+00:00"
    },
    {
      "mmsi": 338531103,
      "name": "MISS AVALON (FB41)",
      "lat": 38.89805833333333,
      "lon": -76.43563166666667,
      "speed": 4.4,
      "course": 242.2,
      "heading": 511,
      "ship_type": null,
      "timestamp": "2026-01-17T20:53:54.178502+00:00"
    },
    {
      "mmsi": 210238000,
      "name": "SOLE",
      "lat": 38.951355,
      "lon": -76.41580166666667,
      "speed": 0,
      "course": 97.6,
      "heading": 179,
      "ship_type": null,
      "timestamp": "2026-01-17T20:53:45.721080+00:00"
    },
    {
      "mmsi": 367083060,
      "name": "CABARET2",
      "lat": 38.967035,
      "lon": -76.47815999999999,
      "speed": 0,
      "course": 0,
      "heading": 0,
      "ship_type": null,
      "timestamp": "2026-01-17T20:53:47.198520+00:00"
    },
    {
      "mmsi": 338846000,
      "name": "LEROY A. MENDONCA",
      "lat": 36.97300333333333,
      "lon": -76.43344666666667,
      "speed": 0,
      "course": 0,
      "heading": 240,
      "ship_type": null,
      "timestamp": "2026-01-17T20:53:46.803081+00:00"
    },
    {
      "mmsi": 366870980,
      "name": "GERI T",
      "lat": 36.919380000000004,
      "lon": -76.34234,
      "speed": 0,
      "course": 108.5,
      "heading": 35,
      "ship_type": null,
      "timestamp": "2026-01-17T20:53:51.556530+00:00"
    },
    {
      "mmsi": 367462360,
      "name": "CINDY R",
      "lat": 36.858846666666665,
      "lon": -76.34698666666667,
      "speed": 0,
      "course": 360,
      "heading": 511,
      "ship_type": null,
      "timestamp": "2026-01-17T20:53:52.626941+00:00"
    },
    {
      "mmsi": 367082130,
      "name": "TIMOTHY MCALLISTER",
      "lat": 36.97074833333333,
      "lon": -76.43283833333334,
      "speed": 0,
      "course": 93.8,
      "heading": 143,
      "ship_type": null,
      "timestamp": "2026-01-17T20:53:52.796437+00:00"
    },
    {
      "mmsi": 368886000,
      "name": "YUMA",
      "lat": 36.866096666666664,
      "lon": -76.31839333333333,
      "speed": 0,
      "course": 360,
      "heading": 511,
      "ship_type": null,
      "timestamp": "2026-01-17T20:53:53.005159+00:00"
    },
    {
      "mmsi": 538011158,
      "name": "AL BATEEN",
      "lat": 36.85816666666666,
      "lon": -76.31856666666665,
      "speed": 0,
      "course": 69.3,
      "heading": 95,
      "ship_type": null,
      "timestamp": "2026-01-17T20:53:53.269168+00:00"
    },
    {
      "mmsi": 368926275,
      "name": "WARSHIP",
      "lat": 36.940128333333334,
      "lon": -76.33333333333333,
      "speed": 0,
      "course": 360,
      "heading": 511,
      "ship_type": null,
      "timestamp": "2026-01-17T20:53:53.810936+00:00"
    }
  ]
}